{
  "display": {
    "icon": {
      "id": "minecraft_add:world_heart"
    },
    "title": {
      "translate": "advancements.world_heart_advancements.title"
    },
    "description": {
      "translate": "advancements.world_heart_advancements.descr"
    },
    "frame": "goal",
    "show_toast": true,
    "announce_to_chat": true,
    "hidden": true
  },
  "criteria": {
    "world_heart_advancements_0": {
      "trigger": "minecraft:inventory_changed",
      "conditions": {
        "items": [
          {
            "items": [
              "minecraft_add:world_heart"
            ],
            "count": {
              "min": 1,
              "max": 4
            }
          }
        ]
      }
    }
  },
  "rewards": {
    "experience": 999
  },
  "parent": "minecraft_add:bedrock_tools_advancements"
}